qubitchem/__init__.py
qubitchem/__version__.py
QubitChem-0.1.0b0.dist-info/LICENSE
QubitChem-0.1.0b0.dist-info/METADATA
QubitChem-0.1.0b0.dist-info/WHEEL
QubitChem-0.1.0b0.dist-info/top_level.txt
QubitChem-0.1.0b0.dist-info/RECORD
