Metadata-Version: 2.1
Name: QubitChem
Version: 0.1.0b0
Summary: Quantum Chemistry solvers on qubits
Home-page: https://github.com/TBA
Author: Yu Zhang
Author-email: zhyhku@gmail.com
License: UNKNOWN
Platform: UNKNOWN
Requires-Python: >=3.6
License-File: LICENSE
Requires-Dist: numpy (<1.26.0,>=1.20.0)
Requires-Dist: scipy (<=1.10.1,>=1.3.0)
